tg_redis_queue/__init__.py
tg_redis_queue/async_redis_que.py
tg_redis_queue/base_redis_que.py
tg_redis_queue/sync_redis_queue.py
tg_redis_queue-1.1.3.dist-info/LICENSE
tg_redis_queue-1.1.3.dist-info/METADATA
tg_redis_queue-1.1.3.dist-info/WHEEL
tg_redis_queue-1.1.3.dist-info/top_level.txt
tg_redis_queue-1.1.3.dist-info/RECORD
