Metadata-Version: 2.1
Name: tg-redis-queue
Version: 1.1.3
Summary: Easy to use redis queue
Home-page: https://gitlab.com/thorgate-public/tg-redis-queue
Author: Sergey Kovalskiy
Author-email: sergey@thorgate.eu
License: UNKNOWN
Platform: UNKNOWN
Classifier: Intended Audience :: Developers
Classifier: Operating System :: OS Independent
Classifier: Programming Language :: Python
Classifier: Programming Language :: Python :: 3
Classifier: Programming Language :: Python :: 3 :: Only
Requires-Python: >=3.6
License-File: LICENSE
Provides-Extra: asyncio
Requires-Dist: aioredis (>=1.3.1) ; extra == 'asyncio'
Provides-Extra: synchronous
Requires-Dist: redis (>=3.2.0) ; extra == 'synchronous'
